nwm/__init__.py
nwm/_version.py
nwm/bmi.py
nwm/cli.py
nwm/nwm.py
nwm-0.1.3.dist-info/LICENSE.txt
nwm-0.1.3.dist-info/METADATA
nwm-0.1.3.dist-info/WHEEL
nwm-0.1.3.dist-info/entry_points.txt
nwm-0.1.3.dist-info/top_level.txt
nwm-0.1.3.dist-info/RECORD
